proxy_pool_redis/KuaiProxyPool.py
proxy_pool_redis/XunProxyPool.py
proxy_pool_redis/__init__.py
proxy_pool_redis/config.py
proxy_pool_redis/log_config.yml
proxy_pool_redis/pool.py
proxy_pool_redis-0.0.15.dist-info/LICENSE
proxy_pool_redis-0.0.15.dist-info/METADATA
proxy_pool_redis-0.0.15.dist-info/WHEEL
proxy_pool_redis-0.0.15.dist-info/top_level.txt
proxy_pool_redis-0.0.15.dist-info/RECORD
