Metadata-Version: 2.1
Name: proxy-pool-redis
Version: 0.0.15
Summary: 爬虫代理IP池
Home-page: https://github.com/ggqshr/proxy_pool_redis
Author: ggq
Author-email: 942490944@qq.com
License: UNKNOWN
Platform: UNKNOWN
Classifier: Programming Language :: Python :: 3
Classifier: License :: OSI Approved :: MIT License
Classifier: Operating System :: OS Independent
Requires-Dist: requests
Requires-Dist: redis
Requires-Dist: PyYAML
Requires-Dist: dataclasses
